renardo/RenardoApp.py
renardo/RenardoTUI.py
renardo/RenardoTUI.tcss
renardo/__init__.py
renardo/__main__.py
renardo/pulsar_mgt.py
renardo/supercollider_mgt/__init__.py
renardo/supercollider_mgt/sc_classes_files.py
renardo/supercollider_mgt/sclang_instances_mgt.py
renardo/widgets/ConfigPane.py
renardo/widgets/RightPane.py
renardo/widgets/TutoTabPane.py
renardo/widgets/__init__.py
renardo-0.9.13.dist-info/METADATA
renardo-0.9.13.dist-info/WHEEL
renardo-0.9.13.dist-info/entry_points.txt
renardo-0.9.13.dist-info/top_level.txt
renardo-0.9.13.dist-info/RECORD
