Metadata-Version: 2.1
Name: renardo
Version: 0.9.13
Summary: Launcher/config editor for Renardo livecoding environment
Home-page: http://renardo.org/
Author: Elie Gavoty
Author-email: eliegavoty@free.fr
License: cc-by-sa-4.0
Requires-Dist: renardo-lib ==0.9.13
Requires-Dist: FoxDotEditor ==0.9.13
Requires-Dist: renardo-gatherer ==0.1.4.dev1
Requires-Dist: psutil
Requires-Dist: textual ==0.79.1
